dummy_package/__init__.py
simba_python-0.0.1rc1.dist-info/METADATA
simba_python-0.0.1rc1.dist-info/WHEEL
simba_python-0.0.1rc1.dist-info/RECORD
